Workbook
Name _xlchart.v1.1: 'Calcs and Graphs'!$B$20:$BG$20
Name _xlchart.v1.0: 'Calcs and Graphs'!$B$19:$BG$19
Name _xlchart.v1.2: 'Calcs and Graphs'!$B$19:$BG$19
Name _xlchart.v1.3: 'Calcs and Graphs'!$B$20:$BG$20

Sheet raw_imf
A1: KEY | B1: DATASET | C1: SERIES_CODE | D1: OBS_MEASURE | E1: COUNTRY | F1: ACCOUNTING_ENTRY | G1: INDICATOR | H1: SECTOR | I1: COUNTERPART_SECTOR | J1: COUNTERPART_COUNTRY | K1: FREQUENCY | L1: SCALE | M1: 1997-S1 | N1: 1997-S2 | O1: 1998-S1 | P1: 1998-S2 | Q1: 1999-S1 | R1: 1999-S2 | S1: 2000-S1 | T1: 2000-S2 | U1: 2001-S1 | V1: 2001-S2 | W1: 2002-S1 | X1: 2002-S2 | Y1: 2003-S1 | Z1: 2003-S2 | AA1: 2004-S1 | AB1: 2004-S2 | AC1: 2005-S1 | AD1: 2005-S2 | AE1: 2006-S1 | AF1: 2006-S2 | AG1: 2007-S1 | AH1: 2007-S2 | AI1: 2008-S1 | AJ1: 2008-S2 | AK1: 2009-S1 | AL1: 2009-S2 | AM1: 2010-S1 | AN1: 2010-S2 | AO1: 2011-S1 | AP1: 2011-S2 | AQ1: 2012-S1 | AR1: 2012-S2 | AS1: 2013-S1 | AT1: 2013-S2 | AU1: 2014-S1 | AV1: 2014-S2 | AW1: 2015-S1 | AX1: 2015-S2 | AY1: 2016-S1 | AZ1: 2016-S2 | BA1: 2017-S1 | BB1: 2017-S2 | BC1: 2018-S1 | BD1: 2018-S2 | BE1: 2019-S1 | BF1: 2019-S2 | BG1: 2020-S1 | BH1: 2020-S2 | BI1: 2021-S1 | BJ1: 2021-S2 | BK1: 2022-S1 | BL1: 2022-S2 | BM1: 2023-S1 | BN1: 2023-S2 | BO1: 2024-S1 | BP1: 2024-S2 | BQ1: 2025-S1 | BR1: 2025-S2
A2: =F2&"|"&G2&"|"&J2&"|"&K2 -> Liabilities|Portfolio investment, Debt securities, Long-term, Positions|Mexico|Half-yearly, semester | B2: IMF.STA:PIP(5.0.0) | C2: NZL.L.P_F3_L_P_USD.S1.S1.MEX.S | D2: OBS_VALUE | E2: New Zealand | F2: Liabilities | G2: Portfolio investment, Debt securities, Long-term, Positions | H2: Total economy | I2: Total economy | J2: Mexico | K2: Half-yearly, semester | L2: Millions | BA2: 0.038095238
A3: =F3&"|"&G3&"|"&J3&"|"&K3 -> Liabilities|Portfolio investment, Debt securities, Long-term, Positions|Finland|Half-yearly, semester | B3: IMF.STA:PIP(5.0.0) | C3: NZL.L.P_F3_L_P_USD.S1.S1.FIN.S | D3: OBS_VALUE | E3: New Zealand | F3: Liabilities | G3: Portfolio investment, Debt securities, Long-term, Positions | H3: Total economy | I3: Total economy | J3: Finland | K3: Half-yearly, semester | L3: Millions
A4: =F4&"|"&G4&"|"&J4&"|"&K4 -> Liabilities|Portfolio investment, Debt securities, Long-term, Positions|Qatar|Half-yearly, semester | B4: IMF.STA:PIP(5.0.0) | C4: NZL.L.P_F3_L_P_USD.S1.S1.QAT.S | D4: OBS_VALUE | E4: New Zealand | F4: Liabilities | G4: Portfolio investment, Debt securities, Long-term, Positions | H4: Total economy | I4: Total economy | J4: Qatar | K4: Half-yearly, semester | L4: Millions | BI4: 0.0076976907 | BJ4: 0.0075152012 | BK4: 0.00683527 | BL4: 0.0069686411
A5: =F5&"|"&G5&"|"&J5&"|"&K5 -> Liabilities|Portfolio investment, Debt securities, Long-term, Positions|Liechtenstein, Principality of|Half-yearly, semester | B5: IMF.STA:PIP(5.0.0) | C5: NZL.L.P_F3_L_P_USD.S1.S1.LIE.S | D5: OBS_VALUE | E5: New Zealand | F5: Liabilities | G5: Portfolio investment, Debt securities, Long-term, Positions | H5: Total economy | I5: Total economy | J5: Liechtenstein, Principality of | K5: Half-yearly, semester | L5: Millions
A6: =F6&"|"&G6&"|"&J6&"|"&K6 -> Liabilities|Portfolio investment, Debt securities, Long-term, Positions|Turks and Caicos Islands|Half-yearly, semester | B6: IMF.STA:PIP(5.0.0) | C6: NZL.L.P_F3_L_P_USD.S1.S1.TCA.S | D6: OBS_VALUE | E6: New Zealand | F6: Liabilities | G6: Portfolio investment, Debt securities, Long-term, Positions | H6: Total economy | I6: Total economy | J6: Turks and Caicos Islands | K6: Half-yearly, semester | L6: Millions
A7: =F7&"|"&G7&"|"&J7&"|"&K7 -> Liabilities|Portfolio investment, Debt securities, Long-term, Positions|Croatia, Republic of|Half-yearly, semester | B7: IMF.STA:PIP(5.0.0) | C7: NZL.L.P_F3_L_P_USD.S1.S1.HRV.S | D7: OBS_VALUE | E7: New Zealand | F7: Liabilities | G7: Portfolio investment, Debt securities, Long-term, Positions | H7: Total economy | I7: Total economy | J7: Croatia, Republic of | K7: Half-yearly, semester | L7: Millions
A8: =F8&"|"&G8&"|"&J8&"|"&K8 -> Liabilities|Portfolio investment, Debt securities, Long-term, Positions|Sweden|Half-yearly, semester | B8: IMF.STA:PIP(5.0.0) | C8: NZL.L.P_F3_L_P_USD.S1.S1.SWE.S | D8: OBS_VALUE | E8: New Zealand | F8: Liabilities | G8: Portfolio investment, Debt securities, Long-term, Positions | H8: Total economy | I8: Total economy | J8: Sweden | K8: Half-yearly, semester | L8: Millions
A9: =F9&"|"&G9&"|"&J9&"|"&K9 -> Liabilities|Portfolio investment, Debt securities, Long-term, Positions|Gibraltar|Half-yearly, semester | B9: IMF.STA:PIP(5.0.0) | C9: NZL.L.P_F3_L_P_USD.S1.S1.GIB.S | D9: OBS_VALUE | E9: New Zealand | F9: Liabilities | G9: Portfolio investment, Debt securities, Long-term, Positions | H9: Total economy | I9: Total economy | J9: Gibraltar | K9: Half-yearly, semester | L9: Millions
A10: =F10&"|"&G10&"|"&J10&"|"&K10 -> Liabilities|Portfolio investment, Debt securities, Long-term, Positions|Libya|Half-yearly, semester | B10: IMF.STA:PIP(5.0.0) | C10: NZL.L.P_F3_L_P_USD.S1.S1.LBY.S | D10: OBS_VALUE | E10: New Zealand | F10: Liabilities | G10: Portfolio investment, Debt securities, Long-term, Positions | H10: Total economy | I10: Total economy | J10: Libya | K10: Half-yearly, semester | L10: Millions
A11: =F11&"|"&G11&"|"&J11&"|"&K11 -> Liabilities|Portfolio investment, Debt securities, Long-term, Positions|Naoero, Republic of|Half-yearly, semester | B11: IMF.STA:PIP(5.0.0) | C11: NZL.L.P_F3_L_P_USD.S1.S1.NRU.S | D11: OBS_VALUE | E11: New Zealand | F11: Liabilities | G11: Portfolio investment, Debt securities, Long-term, Positions | H11: Total economy | I11: Total economy | J11: Naoero, Republic of | K11: Half-yearly, semester | L11: Millions
A12: =F12&"|"&G12&"|"&J12&"|"&K12 -> Liabilities|Portfolio investment, Debt securities, Long-term, Positions|Zimbabwe|Half-yearly, semester | B12: IMF.STA:PIP(5.0.0) | C12: NZL.L.P_F3_L_P_USD.S1.S1.ZWE.S | D12: OBS_VALUE | E12: New Zealand | F12: Liabilities | G12: Portfolio investment, Debt securities, Long-term, Positions | H12: Total economy | I12: Total economy | J12: Zimbabwe | K12: Half-yearly, semester | L12: Millions
A13: =F13&"|"&G13&"|"&J13&"|"&K13 -> Liabilities|Portfolio investment, Debt securities, Long-term, Positions|Bulgaria|Half-yearly, semester | B13: IMF.STA:PIP(5.0.0) | C13: NZL.L.P_F3_L_P_USD.S1.S1.BGR.S | D13: OBS_VALUE | E13: New Zealand | F13: Liabilities | G13: Portfolio investment, Debt securities, Long-term, Positions | H13: Total economy | I13: Total economy | J13: Bulgaria | K13: Half-yearly, semester | L13: Millions
A14: =F14&"|"&G14&"|"&J14&"|"&K14 -> Liabilities|Portfolio investment, Debt securities, Long-term, Positions|Tonga|Half-yearly, semester | B14: IMF.STA:PIP(5.0.0) | C14: NZL.L.P_F3_L_P_USD.S1.S1.TON.S | D14: OBS_VALUE | E14: New Zealand | F14: Liabilities | G14: Portfolio investment, Debt securities, Long-term, Positions | H14: Total economy | I14: Total economy | J14: Tonga | K14: Half-yearly, semester | L14: Millions
A15: =F15&"|"&G15&"|"&J15&"|"&K15 -> Liabilities|Portfolio investment, Debt securities, Long-term, Positions|Iceland|Half-yearly, semester | B15: IMF.STA:PIP(5.0.0) | C15: NZL.L.P_F3_L_P_USD.S1.S1.ISL.S | D15: OBS_VALUE | E15: New Zealand | F15: Liabilities | G15: Portfolio investment, Debt securities, Long-term, Positions | H15: Total economy | I15: Total economy | J15: Iceland | K15: Half-yearly, semester | L15: Millions
A16: =F16&"|"&G16&"|"&J16&"|"&K16 -> Liabilities|Portfolio investment, Debt securities, Long-term, Positions|Greece|Half-yearly, semester | B16: IMF.STA:PIP(5.0.0) | C16: NZL.L.P_F3_L_P_USD.S1.S1.GRC.S | D16: OBS_VALUE | E16: New Zealand | F16: Liabilities | G16: Portfolio investment, Debt securities, Long-term, Positions | H16: Total economy | I16: Total economy | J16: Greece | K16: Half-yearly, semester | L16: Millions
... A23: =F23&"|"&G23&"|"&J23&"|"&K23 -> Liabilities|Portfolio investment, Debt securities, Long-term, Positions|Armenia, Republic of|Half-yearly, semester | B23: IMF.STA:PIP(5.0.0) | C23: NZL.L.P_F3_L_P_USD.S1.S1.ARM.S | D23: OBS_VALUE | E23: New Zealand | F23: Liabilities | G23: Portfolio investment, Debt securities, Long-term, Positions | H23: Total economy | I23: Total economy | J23: Armenia, Republic of | K23: Half-yearly, semester | L23: Millions
A24: =F24&"|"&G24&"|"&J24&"|"&K24 -> Liabilities|Portfolio investment, Debt securities, Long-term, Positions|Malta|Half-yearly, semester | B24: IMF.STA:PIP(5.0.0) | C24: NZL.L.P_F3_L_P_USD.S1.S1.MLT.S | D24: OBS_VALUE | E24: New Zealand | F24: Liabilities | G24: Portfolio investment, Debt securities, Long-term, Positions | H24: Total economy | I24: Total economy | J24: Malta | K24: Half-yearly, semester | L24: Millions | AZ24: 0.13727266 | BA24: 0.14578755 | BB24: 0.14833215 | BC24: 0.13953488 | BD24: 0.13426423
A25: =F25&"|"&G25&"|"&J25&"|"&K25 -> Liabilities|Portfolio investment, Debt securities, Long-term, Positions|Kenya|Half-yearly, semester | B25: IMF.STA:PIP(5.0.0) | C25: NZL.L.P_F3_L_P_USD.S1.S1.KEN.S | D25: OBS_VALUE | E25: New Zealand | F25: Liabilities | G25: Portfolio investment, Debt securities, Long-term, Positions | H25: Total economy | I25: Total economy | J25: Kenya | K25: Half-yearly, semester | L25: Millions | AZ25: 0.14911853 | BA25: 0.15677656 | BB25: 0.15188077 | BC25: 0.076845298 | BD25: 0.14366273
A26: =F26&"|"&G26&"|"&J26&"|"&K26 -> Liabilities|Portfolio investment, Debt securities, Long-term, Positions|Isle of Man|Half-yearly, semester | B26: IMF.STA:PIP(5.0.0) | C26: NZL.L.P_F3_L_P_USD.S1.S1.IMN.S | D26: OBS_VALUE | E26: New Zealand | F26: Liabilities | G26: Portfolio investment, Debt securities, Long-term, Positions | H26: Total economy | I26: Total economy | J26: Isle of Man | K26: Half-yearly, semester | L26: Millions
A27: =F27&"|"&G27&"|"&J27&"|"&K27 -> Liabilities|Portfolio investment, Debt securities, Long-term, Positions|American Samoa|Half-yearly, semester | B27: IMF.STA:PIP(5.0.0) | C27: NZL.L.P_F3_L_P_USD.S1.S1.ASM.S | D27: OBS_VALUE | E27: New Zealand | F27: Liabilities | G27: Portfolio investment, Debt securities, Long-term, Positions | H27: Total economy | I27: Total economy | J27: American Samoa | K27: Half-yearly, semester | L27: Millions
A28: =F28&"|"&G28&"|"&J28&"|"&K28 -> Liabilities|Portfolio investment, Debt securities, Long-term, Positions|Venezuela, República Bolivariana de|Half-yearly, semester | B28: IMF.STA:PIP(5.0.0) | C28: NZL.L.P_F3_L_P_USD.S1.S1.VEN.S | D28: OBS_VALUE | E28: New Zealand | F28: Liabilities | G28: Portfolio investment, Debt securities, Long-term, Positions | H28: Total economy | I28: Total economy | J28: Venezuela, República Bolivariana de | K28: Half-yearly, semester | L28: Millions
A29: =F29&"|"&G29&"|"&J29&"|"&K29 -> Liabilities|Portfolio investment, Debt securities, Long-term, Positions|Chile|Half-yearly, semester | B29: IMF.STA:PIP(5.0.0) | C29: NZL.L.P_F3_L_P_USD.S1.S1.CHL.S | D29: OBS_VALUE | E29: New Zealand | F29: Liabilities | G29: Portfolio investment, Debt securities, Long-term, Positions | H29: Total economy | I29: Total economy | J29: Chile | K29: Half-yearly, semester | L29: Millions
A30: =F30&"|"&G30&"|"&J30&"|"&K30 -> Liabilities|Portfolio investment, Debt securities, Long-term, Positions|Bangladesh|Half-yearly, semester | B30: IMF.STA:PIP(5.0.0) | C30: NZL.L.P_F3_L_P_USD.S1.S1.BGD.S | D30: OBS_VALUE | E30: New Zealand | F30: Liabilities | G30: Portfolio investment, Debt securities, Long-term, Positions | H30: Total economy | I30: Total economy | J30: Bangladesh | K30: Half-yearly, semester | L30: Millions
A31: =F31&"|"&G31&"|"&J31&"|"&K31 -> Liabilities|Portfolio investment, Debt securities, Long-term, Positions|Macao Special Administrative Region, People's Republic of China|Half-yearly, semester | B31: IMF.STA:PIP(5.0.0) | C31: NZL.L.P_F3_L_P_USD.S1.S1.MAC.S | D31: OBS_VALUE | E31: New Zealand | F31: Liabilities | G31: Portfolio investment, Debt securities, Long-term, Positions | H31: Total economy | I31: Total economy | J31: Macao Special Administrative Region, People's Republic of China | K31: Half-yearly, semester | L31: Millions
A32: =F32&"|"&G32&"|"&J32&"|"&K32 -> Liabilities|Portfolio investment, Debt securities, Long-term, Positions|International Organizations|Half-yearly, semester | B32: IMF.STA:PIP(5.0.0) | C32: NZL.L.P_F3_L_P_USD.S1.S1.TX091.S | D32: OBS_VALUE | E32: New Zealand | F32: Liabilities | G32: Portfolio investment, Debt securities, Long-term, Positions | H32: Total economy | I32: Total economy | J32: International Organizations | K32: Half-yearly, semester | L32: Millions | AN32: 0
A33: =F33&"|"&G33&"|"&J33&"|"&K33 -> Liabilities|Portfolio investment, Debt securities, Long-term, Positions|Brunei Darussalam|Half-yearly, semester | B33: IMF.STA:PIP(5.0.0) | C33: NZL.L.P_F3_L_P_USD.S1.S1.BRN.S | D33: OBS_VALUE | E33: New Zealand | F33: Liabilities | G33: Portfolio investment, Debt securities, Long-term, Positions | H33: Total economy | I33: Total economy | J33: Brunei Darussalam | K33: Half-yearly, semester | L33: Millions
A34: =F34&"|"&G34&"|"&J34&"|"&K34 -> Liabilities|Portfolio investment, Debt securities, Long-term, Positions|Andorra, Principality of|Half-yearly, semester | B34: IMF.STA:PIP(5.0.0) | C34: NZL.L.P_F3_L_P_USD.S1.S1.AND.S | D34: OBS_VALUE | E34: New Zealand | F34: Liabilities | G34: Portfolio investment, Debt securities, Long-term, Positions | H34: Total economy | I34: Total economy | J34: Andorra, Principality of | K34: Half-yearly, semester | L34: Millions
A35: =F35&"|"&G35&"|"&J35&"|"&K35 -> Liabilities|Portfolio investment, Debt securities, Long-term, Positions|Ukraine|Half-yearly, semester | B35: IMF.STA:PIP(5.0.0) | C35: NZL.L.P_F3_L_P_USD.S1.S1.UKR.S | D35: OBS_VALUE | E35: New Zealand | F35: Liabilities | G35: Portfolio investment, Debt securities, Long-term, Positions | H35: Total economy | I35: Total economy | J35: Ukraine | K35: Half-yearly, semester | L35: Millions
A36: =F36&"|"&G36&"|"&J36&"|"&K36 -> Liabilities|Portfolio investment, Debt securities, Long-term, Positions|Samoa|Half-yearly, semester | B36: IMF.STA:PIP(5.0.0) | C36: NZL.L.P_F3_L_P_USD.S1.S1.WSM.S | D36: OBS_VALUE | E36: New Zealand | F36: Liabilities | G36: Portfolio investment, Debt securities, Long-term, Positions | H36: Total economy | I36: Total economy | J36: Samoa | K36: Half-yearly, semester | L36: Millions
A37: =F37&"|"&G37&"|"&J37&"|"&K37 -> Liabilities|Portfolio investment, Debt securities, Long-term, Positions|Bahamas, The|Half-yearly, semester | B37: IMF.STA:PIP(5.0.0) | C37: NZL.L.P_F3_L_P_USD.S1.S1.BHS.S | D37: OBS_VALUE | E37: New Zealand | F37: Liabilities | G37: Portfolio investment, Debt securities, Long-term, Positions | H37: Total economy | I37: Total economy | J37: Bahamas, The | K37: Half-yearly, semester | L37: Millions
A38: =F38&"|"&G38&"|"&J38&"|"&K38 -> Liabilities|Portfolio investment, Debt securities, Long-term, Positions|Solomon Islands|Half-yearly, semester | B38: IMF.STA:PIP(5.0.0) | C38: NZL.L.P_F3_L_P_USD.S1.S1.SLB.S | D38: OBS_VALUE | E38: New Zealand | F38: Liabilities | G38: Portfolio investment, Debt securities, Long-term, Positions | H38: Total economy | I38: Total economy | J38: Solomon Islands | K38: Half-yearly, semester | L38: Millions
A39: =F39&"|"&G39&"|"&J39&"|"&K39 -> Liabilities|Portfolio investment, Debt securities, Long-term, Positions|Poland, Republic of|Half-yearly, semester | B39: IMF.STA:PIP(5.0.0) | C39: NZL.L.P_F3_L_P_USD.S1.S1.POL.S | D39: OBS_VALUE | E39: New Zealand | F39: Liabilities | G39: Portfolio investment, Debt securities, Long-term, Positions | H39: Total economy | I39: Total economy | J39: Poland, Republic of | K39: Half-yearly, semester | L39: Millions
A40: =F40&"|"&G40&"|"&J40&"|"&K40 -> Liabilities|Portfolio investment, Debt securities, Long-term, Positions|Türkiye, Republic of|Half-yearly, semester | B40: IMF.STA:PIP(5.0.0) | C40: NZL.L.P_F3_L_P_USD.S1.S1.TUR.S | D40: OBS_VALUE | E40: New Zealand | F40: Liabilities | G40: Portfolio investment, Debt securities, Long-term, Positions | H40: Total economy | I40: Total economy | J40: Türkiye, Republic of | K40: Half-yearly, semester | L40: Millions
A41: =F41&"|"&G41&"|"&J41&"|"&K41 -> Liabilities|Portfolio investment, Debt securities, Long-term, Positions|Bhutan|Half-yearly, semester | B41: IMF.STA:PIP(5.0.0) | C41: NZL.L.P_F3_L_P_USD.S1.S1.BTN.S | D41: OBS_VALUE | E41: New Zealand | F41: Liabilities | G41: Portfolio investment, Debt securities, Long-term, Positions | H41: Total economy | I41: Total economy | J41: Bhutan | K41: Half-yearly, semester | L41: Millions
A42: =F42&"|"&G42&"|"&J42&"|"&K42 -> Liabilities|Portfolio investment, Debt securities, Long-term, Positions|Vietnam|Half-yearly, semester | B42: IMF.STA:PIP(5.0.0) | C42: NZL.L.P_F3_L_P_USD.S1.S1.VNM.S | D42: OBS_VALUE | E42: New Zealand | F42: Liabilities | G42: Portfolio investment, Debt securities, Long-term, Positions | H42: Total economy | I42: Total economy | J42: Vietnam | K42: Half-yearly, semester | L42: Millions
A43: =F43&"|"&G43&"|"&J43&"|"&K43 -> Liabilities|Portfolio investment, Debt securities, Long-term, Positions|Pakistan|Half-yearly, semester | B43: IMF.STA:PIP(5.0.0) | C43: NZL.L.P_F3_L_P_USD.S1.S1.PAK.S | D43: OBS_VALUE | E43: New Zealand | F43: Liabilities | G43: Portfolio investment, Debt securities, Long-term, Positions | H43: Total economy | I43: Total economy | J43: Pakistan | K43: Half-yearly, semester | L43: Millions
A44: =F44&"|"&G44&"|"&J44&"|"&K44 -> Liabilities|Portfolio investment, Debt securities, Positions|Suriname|Half-yearly, semester | B44: IMF.STA:PIP(5.0.0) | C44: NZL.L.P_F3_P_USD.S1.S1.SUR.S | D44: OBS_VALUE | E44: New Zealand | F44: Liabilities | G44: Portfolio investment, Debt securities, Positions | H44: Total economy | I44: Total economy | J44: Suriname | K44: Half-yearly, semester | L44: Millions | AL44: 0 | BI44: 0 | BM44: 0 | BO44: 0
A45: =F45&"|"&G45&"|"&J45&"|"&K45 -> Liabilities|Portfolio investment, Debt securities, Positions|Grenada|Half-yearly, semester | B45: IMF.STA:PIP(5.0.0) | C45: NZL.L.P_F3_P_USD.S1.S1.GRD.S | D45: OBS_VALUE | E45: New Zealand | F45: Liabilities | G45: Portfolio investment, Debt securities, Positions | H45: Total economy | I45: Total economy | J45: Grenada | K45: Half-yearly, semester | L45: Millions | AL45: 0 | BI45: 0 | BM45: 0 | BO45: 0
A46: =F46&"|"&G46&"|"&J46&"|"&K46 -> Liabilities|Portfolio investment, Debt securities, Positions|St. Kitts and Nevis|Half-yearly, semester | B46: IMF.STA:PIP(5.0.0) | C46: NZL.L.P_F3_P_USD.S1.S1.KNA.S | D46: OBS_VALUE | E46: New Zealand | F46: Liabilities | G46: Portfolio investment, Debt securities, Positions | H46: Total economy | I46: Total economy | J46: St. Kitts and Nevis | K46: Half-yearly, semester | L46: Millions | AL46: 0 | BI46: 0 | BM46: 0 | BO46: 0
A47: =F47&"|"&G47&"|"&J47&"|"&K47 -> Liabilities|Portfolio investment, Debt securities, Positions|Netherlands Antilles|Half-yearly, semester | B47: IMF.STA:PIP(5.0.0) | C47: NZL.L.P_F3_P_USD.S1.S1.ANT.S | D47: OBS_VALUE | E47: New Zealand | F47: Liabilities | G47: Portfolio investment, Debt securities, Positions | H47: Total economy | I47: Total economy | J47: Netherlands Antilles | K47: Half-yearly, semester | L47: Millions | AL47: 0
A48: =F48&"|"&G48&"|"&J48&"|"&K48 -> Liabilities|Portfolio investment, Debt securities, Long-term, Positions|British Virgin Islands|Half-yearly, semester | B48: IMF.STA:PIP(5.0.0) | C48: NZL.L.P_F3_L_P_USD.S1.S1.VGB.S | D48: OBS_VALUE | E48: New Zealand | F48: Liabilities | G48: Portfolio investment, Debt securities, Long-term, Positions | H48: Total economy | I48: Total economy | J48: British Virgin Islands | K48: Half-yearly, semester | L48: Millions
A49: =F49&"|"&G49&"|"&J49&"|"&K49 -> Liabilities|Portfolio investment, Debt securities, Long-term, Positions|Norfolk Island|Half-yearly, semester | B49: IMF.STA:PIP(5.0.0) | C49: NZL.L.P_F3_L_P_USD.S1.S1.NFK.S | D49: OBS_VALUE | E49: New Zealand | F49: Liabilities | G49: Portfolio investment, Debt securities, Long-term, Positions | H49: Total economy | I49: Total economy | J49: Norfolk Island | K49: Half-yearly, semester | L49: Millions
A50: =F50&"|"&G50&"|"&J50&"|"&K50 -> Liabilities|Portfolio investment, Debt securities, Positions|Nicaragua|Half-yearly, semester | B50: IMF.STA:PIP(5.0.0) | C50: NZL.L.P_F3_P_USD.S1.S1.NIC.S | D50: OBS_VALUE | E50: New Zealand | F50: Liabilities | G50: Portfolio investment, Debt securities, Positions | H50: Total economy | I50: Total economy | J50: Nicaragua | K50: Half-yearly, semester | L50: Millions | AL50: 0 | BI50: 0 | BM50: 0 | BO50: 0
A51: =F51&"|"&G51&"|"&J51&"|"&K51 -> Liabilities|Portfolio investment, Debt securities, Long-term, Positions|Hungary|Half-yearly, semester | B51: IMF.STA:PIP(5.0.0) | C51: NZL.L.P_F3_L_P_USD.S1.S1.HUN.S | D51: OBS_VALUE | E51: New Zealand | F51: Liabilities | G51: Portfolio investment, Debt securities, Long-term, Positions | H51: Total economy | I51: Total economy | J51: Hungary | K51: Half-yearly, semester | L51: Millions
A52: =F52&"|"&G52&"|"&J52&"|"&K52 -> Liabilities|Portfolio investment, Debt securities, Positions|Puerto Rico|Half-yearly, semester | B52: IMF.STA:PIP(5.0.0) | C52: NZL.L.P_F3_P_USD.S1.S1.PRI.S | D52: OBS_VALUE | E52: New Zealand | F52: Liabilities | G52: Portfolio investment, Debt securities, Positions | H52: Total economy | I52: Total economy | J52: Puerto Rico | K52: Half-yearly, semester | L52: Millions | AL52: 0 | BI52: 0 | BM52: 0 | BO52: 0
A53: =F53&"|"&G53&"|"&J53&"|"&K53 -> Liabilities|Portfolio investment, Debt securities, Positions|Sweden|Half-yearly, semester | B53: IMF.STA:PIP(5.0.0) | C53: NZL.L.P_F3_P_USD.S1.S1.SWE.S | D53: OBS_VALUE | E53: New Zealand | F53: Liabilities | G53: Portfolio investment, Debt securities, Positions | H53: Total economy | I53: Total economy | J53: Sweden | K53: Half-yearly, semester | L53: Millions | AL53: 0 | BI53: 0 | BM53: 0 | BO53: 0
A54: =F54&"|"&G54&"|"&J54&"|"&K54 -> Liabilities|Portfolio investment, Debt securities, Positions|Trinidad and Tobago|Half-yearly, semester | B54: IMF.STA:PIP(5.0.0) | C54: NZL.L.P_F3_P_USD.S1.S1.TTO.S | D54: OBS_VALUE | E54: New Zealand | F54: Liabilities | G54: Portfolio investment, Debt securities, Positions | H54: Total economy | I54: Total economy | J54: Trinidad and Tobago | K54: Half-yearly, semester | L54: Millions | AL54: 0 | BI54: 0 | BM54: 0 | BO54: 0
A55: =F55&"|"&G55&"|"&J55&"|"&K55 -> Liabilities|Portfolio investment, Debt securities, Positions|Finland|Half-yearly, semester | B55: IMF.STA:PIP(5.0.0) | C55: NZL.L.P_F3_P_USD.S1.S1.FIN.S | D55: OBS_VALUE | E55: New Zealand | F55: Liabilities | G55: Portfolio investment, Debt securities, Positions | H55: Total economy | I55: Total economy | J55: Finland | K55: Half-yearly, semester | L55: Millions | AL55: 0 | BI55: 0 | BM55: 0 | BO55: 0
A56: =F56&"|"&G56&"|"&J56&"|"&K56 -> Liabilities|Portfolio investment, Debt securities, Positions|Bonaire, Saint Eustatius and Saba|Half-yearly, semester | B56: IMF.STA:PIP(5.0.0) | C56: NZL.L.P_F3_P_USD.S1.S1.BES.S | D56: OBS_VALUE | E56: New Zealand | F56: Liabilities | G56: Portfolio investment, Debt securities, Positions | H56: Total economy | I56: Total economy | J56: Bonaire, Saint Eustatius and Saba | K56: Half-yearly, semester | L56: Millions | BI56: 0 | BM56: 0 | BO56: 0
A57: =F57&"|"&G57&"|"&J57&"|"&K57 -> Liabilities|Portfolio investment, Debt securities, Positions|Iceland|Half-yearly, semester | B57: IMF.STA:PIP(5.0.0) | C57: NZL.L.P_F3_P_USD.S1.S1.ISL.S | D57: OBS_VALUE | E57: New Zealand | F57: Liabilities | G57: Portfolio investment, Debt securities, Positions | H57: Total economy | I57: Total economy | J57: Iceland | K57: Half-yearly, semester | L57: Millions | AL57: 0 | BI57: 0 | BM57: 0 | BO57: 0
A58: =F58&"|"&G58&"|"&J58&"|"&K58 -> Liabilities|Portfolio investment, Debt securities, Positions|Antigua and Barbuda|Half-yearly, semester | B58: IMF.STA:PIP(5.0.0) | C58: NZL.L.P_F3_P_USD.S1.S1.ATG.S | D58: OBS_VALUE | E58: New Zealand | F58: Liabilities | G58: Portfolio investment, Debt securities, Positions | H58: Total economy | I58: Total economy | J58: Antigua and Barbuda | K58: Half-yearly, semester | L58: Millions | AL58: 0 | BI58: 0 | BM58: 0 | BO58: 0
A59: =F59&"|"&G59&"|"&J59&"|"&K59 -> Liabilities|Portfolio investment, Debt securities, Positions|Peru|Half-yearly, semester | B59: IMF.STA:PIP(5.0.0) | C59: NZL.L.P_F3_P_USD.S1.S1.PER.S | D59: OBS_VALUE | E59: New Zealand | F59: Liabilities | G59: Portfolio investment, Debt securities, Positions | H59: Total economy | I59: Total economy | J59: Peru | K59: Half-yearly, semester | L59: Millions | AL59: 0 | BI59: 0 | BM59: 0 | BO59: 0
A60: =F60&"|"&G60&"|"&J60&"|"&K60 -> Liabilities|Portfolio investment, Debt securities, Long-term, Positions|Egypt, Arab Republic of|Half-yearly, semester | B60: IMF.STA:PIP(5.0.0) | C60: NZL.L.P_F3_L_P_USD.S1.S1.EGY.S | D60: OBS_VALUE | E60: New Zealand | F60: Liabilities | G60: Portfolio investment, Debt securities, Long-term, Positions | H60: Total economy | I60: Total economy | J60: Egypt, Arab Republic of | K60: Half-yearly, semester | L60: Millions
A61: =F61&"|"&G61&"|"&J61&"|"&K61 -> Liabilities|Portfolio investment, Debt securities, Long-term, Positions|Cambodia|Half-yearly, semester | B61: IMF.STA:PIP(5.0.0) | C61: NZL.L.P_F3_L_P_USD.S1.S1.KHM.S | D61: OBS_VALUE | E61: New Zealand | F61: Liabilities | G61: Portfolio investment, Debt securities, Long-term, Positions | H61: Total economy | I61: Total economy | J61: Cambodia | K61: Half-yearly, semester | L61: Millions
A62: =F62&"|"&G62&"|"&J62&"|"&K62 -> Liabilities|Portfolio investment, Debt securities, Long-term, Positions|Slovak Republic|Half-yearly, semester | B62: IMF.STA:PIP(5.0.0) | C62: NZL.L.P_F3_L_P_USD.S1.S1.SVK.S | D62: OBS_VALUE | E62: New Zealand | F62: Liabilities | G62: Portfolio investment, Debt securities, Long-term, Positions | H62: Total economy | I62: Total economy | J62: Slovak Republic | K62: Half-yearly, semester | L62: Millions
A63: =F63&"|"&G63&"|"&J63&"|"&K63 -> Liabilities|Portfolio investment, Debt securities, Positions|Falkland Islands (Malvinas)|Half-yearly, semester | B63: IMF.STA:PIP(5.0.0) | C63: NZL.L.P_F3_P_USD.S1.S1.FLK.S | D63: OBS_VALUE | E63: New Zealand | F63: Liabilities | G63: Portfolio investment, Debt securities, Positions | H63: Total economy | I63: Total economy | J63: Falkland Islands (Malvinas) | K63: Half-yearly, semester | L63: Millions | AL63: 0 | BI63: 0 | BM63: 0 | BO63: 0
A64: =F64&"|"&G64&"|"&J64&"|"&K64 -> Liabilities|Portfolio investment, Debt securities, Positions|Uruguay|Half-yearly, semester | B64: IMF.STA:PIP(5.0.0) | C64: NZL.L.P_F3_P_USD.S1.S1.URY.S | D64: OBS_VALUE | E64: New Zealand | F64: Liabilities | G64: Portfolio investment, Debt securities, Positions | H64: Total economy | I64: Total economy | J64: Uruguay | K64: Half-yearly, semester | L64: Millions | AL64: 0 | BI64: 0 | BM64: 0 | BO64: 0
A65: =F65&"|"&G65&"|"&J65&"|"&K65 -> Liabilities|Portfolio investment, Debt securities, Long-term, Positions|Kazakhstan, Republic of|Half-yearly, semester | B65: IMF.STA:PIP(5.0.0) | C65: NZL.L.P_F3_L_P_USD.S1.S1.KAZ.S | D65: OBS_VALUE | E65: New Zealand | F65: Liabilities | G65: Portfolio investment, Debt securities, Long-term, Positions | H65: Total economy | I65: Total economy | J65: Kazakhstan, Republic of | K65: Half-yearly, semester | L65: Millions
A66: =F66&"|"&G66&"|"&J66&"|"&K66 -> Liabilities|Portfolio investment, Debt securities, Positions|United States Virgin Islands|Half-yearly, semester | B66: IMF.STA:PIP(5.0.0) | C66: NZL.L.P_F3_P_USD.S1.S1.VIR.S | D66: OBS_VALUE | E66: New Zealand | F66: Liabilities | G66: Portfolio investment, Debt securities, Positions | H66: Total economy | I66: Total economy | J66: United States Virgin Islands | K66: Half-yearly, semester | L66: Millions | AL66: 0 | BI66: 0 | BM66: 0 | BO66: 0
A67: =F67&"|"&G67&"|"&J67&"|"&K67 -> Liabilities|Portfolio investment, Debt securities, Long-term, Positions|Cyprus|Half-yearly, semester | B67: IMF.STA:PIP(5.0.0) | C67: NZL.L.P_F3_L_P_USD.S1.S1.CYP.S | D67: OBS_VALUE | E67: New Zealand | F67: Liabilities | G67: Portfolio investment, Debt securities, Long-term, Positions | H67: Total economy | I67: Total economy | J67: Cyprus | K67: Half-yearly, semester | L67: Millions
A68: =F68&"|"&G68&"|"&J68&"|"&K68 -> Liabilities|Portfolio investment, Debt securities, Positions|Holy See|Half-yearly, semester | B68: IMF.STA:PIP(5.0.0) | C68: NZL.L.P_F3_P_USD.S1.S1.VAT.S | D68: OBS_VALUE | E68: New Zealand | F68: Liabilities | G68: Portfolio investment, Debt securities, Positions | H68: Total economy | I68: Total economy | J68: Holy See | K68: Half-yearly, semester | L68: Millions | AL68: 0 | BI68: 0 | BM68: 0 | BO68: 0
A69: =F69&"|"&G69&"|"&J69&"|"&K69 -> Liabilities|Portfolio investment, Debt securities, Positions|Argentina|Half-yearly, semester | B69: IMF.STA:PIP(5.0.0) | C69: NZL.L.P_F3_P_USD.S1.S1.ARG.S | D69: OBS_VALUE | E69: New Zealand | F69: Liabilities | G69: Portfolio investment, Debt securities, Positions | H69: Total economy | I69: Total economy | J69: Argentina | K69: Half-yearly, semester | L69: Millions | AL69: 0 | BI69: 0 | BM69: 0 | BO69: 0
A70: =F70&"|"&G70&"|"&J70&"|"&K70 -> Liabilities|Portfolio investment, Debt securities, Positions|St. Lucia|Half-yearly, semester | B70: IMF.STA:PIP(5.0.0) | C70: NZL.L.P_F3_P_USD.S1.S1.LCA.S | D70: OBS_VALUE | E70: New Zealand | F70: Liabilities | G70: Portfolio investment, Debt securities, Positions | H70: Total economy | I70: Total economy | J70: St. Lucia | K70: Half-yearly, semester | L70: Millions | AL70: 0 | BI70: 0 | BM70: 0 | BO70: 0
A71: =F71&"|"&G71&"|"&J71&"|"&K71 -> Liabilities|Portfolio investment, Debt securities, Positions|Türkiye, Republic of|Half-yearly, semester | B71: IMF.STA:PIP(5.0.0) | C71: NZL.L.P_F3_P_USD.S1.S1.TUR.S | D71: OBS_VALUE | E71: New Zealand | F71: Liabilities | G71: Portfolio investment, Debt securities, Positions | H71: Total economy | I71: Total economy | J71: Türkiye, Republic of | K71: Half-yearly, semester | L71: Millions | AL71: 0 | BI71: 0 | BM71: 0 | BO71: 0
A72: =F72&"|"&G72&"|"&J72&"|"&K72 -> Liabilities|Portfolio investment, Debt securities, Positions|Brazil|Half-yearly, semester | B72: IMF.STA:PIP(5.0.0) | C72: NZL.L.P_F3_P_USD.S1.S1.BRA.S | D72: OBS_VALUE | E72: New Zealand | F72: Liabilities | G72: Portfolio investment, Debt securities, Positions | H72: Total economy | I72: Total economy | J72: Brazil | K72: Half-yearly, semester | L72: Millions | AL72: 0 | BI72: 0 | BM72: 0 | BO72: 0
A73: =F73&"|"&G73&"|"&J73&"|"&K73 -> Liabilities|Portfolio investment, Debt securities, Positions|Curaçao, Kingdom of the Netherlands|Half-yearly, semester | B73: IMF.STA:PIP(5.0.0) | C73: NZL.L.P_F3_P_USD.S1.S1.CUW.S | D73: OBS_VALUE | E73: New Zealand | F73: Liabilities | G73: Portfolio investment, Debt securities, Positions | H73: Total economy | I73: Total economy | J73: Curaçao, Kingdom of the Netherlands | K73: Half-yearly, semester | L73: Millions | BI73: 0 | BM73: 0 | BO73: 0
A74: =F74&"|"&G74&"|"&J74&"|"&K74 -> Liabilities|Portfolio investment, Debt securities, Positions|Bahamas, The|Half-yearly, semester | B74: IMF.STA:PIP(5.0.0) | C74: NZL.L.P_F3_P_USD.S1.S1.BHS.S | D74: OBS_VALUE | E74: New Zealand | F74: Liabilities | G74: Portfolio investment, Debt securities, Positions | H74: Total economy | I74: Total economy | J74: Bahamas, The | K74: Half-yearly, semester | L74: Millions | AL74: 0 | BI74: 0 | BM74: 0 | BO74: 0
A75: =F75&"|"&G75&"|"&J75&"|"&K75 -> Liabilities|Portfolio investment, Debt securities, Positions|Montserrat, United Kingdom-British Overseas Territory|Half-yearly, semester | B75: IMF.STA:PIP(5.0.0) | C75: NZL.L.P_F3_P_USD.S1.S1.MSR.S | D75: OBS_VALUE | E75: New Zealand | F75: Liabilities | G75: Portfolio investment, Debt securities, Positions | H75: Total economy | I75: Total economy | J75: Montserrat, United Kingdom-British Overseas Territory | K75: Half-yearly, semester | L75: Millions | AL75: 0 | BI75: 0 | BM75: 0 | BO75: 0
A76: =F76&"|"&G76&"|"&J76&"|"&K76 -> Liabilities|Portfolio investment, Debt securities, Positions|Isle of Man|Half-yearly, semester | B76: IMF.STA:PIP(5.0.0) | C76: NZL.L.P_F3_P_USD.S1.S1.IMN.S | D76: OBS_VALUE | E76: New Zealand | F76: Liabilities | G76: Portfolio investment, Debt securities, Positions | H76: Total economy | I76: Total economy | J76: Isle of Man | K76: Half-yearly, semester | L76: Millions | AL76: 0 | BI76: 0 | BM76: 0
A77: =F77&"|"&G77&"|"&J77&"|"&K77 -> Liabilities|Portfolio investment, Debt securities, Long-term, Positions|Malawi|Half-yearly, semester | B77: IMF.STA:PIP(5.0.0) | C77: NZL.L.P_F3_L_P_USD.S1.S1.MWI.S | D77: OBS_VALUE | E77: New Zealand | F77: Liabilities | G77: Portfolio investment, Debt securities, Long-term, Positions | H77: Total economy | I77: Total economy | J77: Malawi | K77: Half-yearly, semester | L77: Millions
A78: =F78&"|"&G78&"|"&J78&"|"&K78 -> Liabilities|Portfolio investment, Debt securities, Long-term, Positions|Oman|Half-yearly, semester | B78: IMF.STA:PIP(5.0.0) | C78: NZL.L.P_F3_L_P_USD.S1.S1.OMN.S | D78: OBS_VALUE | E78: New Zealand | F78: Liabilities | G78: Portfolio investment, Debt securities, Long-term, Positions | H78: Total economy | I78: Total economy | J78: Oman | K78: Half-yearly, semester | L78: Millions
A79: =F79&"|"&G79&"|"&J79&"|"&K79 -> Liabilities|Portfolio investment, Debt securities, Positions|El Salvador|Half-yearly, semester | B79: IMF.STA:PIP(5.0.0) | C79: NZL.L.P_F3_P_USD.S1.S1.SLV.S | D79: OBS_VALUE | E79: New Zealand | F79: Liabilities | G79: Portfolio investment, Debt securities, Positions | H79: Total economy | I79: Total economy | J79: El Salvador | K79: Half-yearly, semester | L79: Millions | AL79: 0 | BI79: 0 | BM79: 0 | BO79: 0
A80: =F80&"|"&G80&"|"&J80&"|"&K80 -> Liabilities|Portfolio investment, Debt securities, Positions|Panama|Half-yearly, semester | B80: IMF.STA:PIP(5.0.0) | C80: NZL.L.P_F3_P_USD.S1.S1.PAN.S | D80: OBS_VALUE | E80: New Zealand | F80: Liabilities | G80: Portfolio investment, Debt securities, Positions | H80: Total economy | I80: Total economy | J80: Panama | K80: Half-yearly, semester | L80: Millions | AL80: 0 | BI80: 0 | BM80: 0 | BO80: 0
A81: =F81&"|"&G81&"|"&J81&"|"&K81 -> Liabilities|Portfolio investment, Debt securities, Positions|Andorra, Principality of|Half-yearly, semester | B81: IMF.STA:PIP(5.0.0) | C81: NZL.L.P_F3_P_USD.S1.S1.AND.S | D81: OBS_VALUE | E81: New Zealand | F81: Liabilities | G81: Portfolio investment, Debt securities, Positions | H81: Total economy | I81: Total economy | J81: Andorra, Principality of | K81: Half-yearly, semester | L81: Millions | AL81: 0 | BI81: 0 | BM81: 0 | BO81: 0
A82: =F82&"|"&G82&"|"&J82&"|"&K82 -> Liabilities|Portfolio investment, Debt securities, Positions|Dominican Republic|Half-yearly, semester | B82: IMF.STA:PIP(5.0.0) | C82: NZL.L.P_F3_P_USD.S1.S1.DOM.S | D82: OBS_VALUE | E82: New Zealand | F82: Liabilities | G82: Portfolio investment, Debt securities, Positions | H82: Total economy | I82: Total economy | J82: Dominican Republic | K82: Half-yearly, semester | L82: Millions | AL82: 0 | BI82: 0 | BM82: 0 | BO82: 0
A83: =F83&"|"&G83&"|"&J83&"|"&K83 -> Liabilities|Portfolio investment, Debt securities, Long-term, Positions|Israel|Half-yearly, semester | B83: IMF.STA:PIP(5.0.0) | C83: NZL.L.P_F3_L_P_USD.S1.S1.ISR.S | D83: OBS_VALUE | E83: New Zealand | F83: Liabilities | G83: Portfolio investment, Debt securities, Long-term, Positions | H83: Total economy | I83: Total economy | J83: Israel | K83: Half-yearly, semester | L83: Millions
A84: =F84&"|"&G84&"|"&J84&"|"&K84 -> Liabilities|Portfolio investment, Debt securities, Long-term, Positions|Papua New Guinea|Half-yearly, semester | B84: IMF.STA:PIP(5.0.0) | C84: NZL.L.P_F3_L_P_USD.S1.S1.PNG.S | D84: OBS_VALUE | E84: New Zealand | F84: Liabilities | G84: Portfolio investment, Debt securities, Long-term, Positions | H84: Total economy | I84: Total economy | J84: Papua New Guinea | K84: Half-yearly, semester | L84: Millions | AZ84: 0.36234409
A85: =F85&"|"&G85&"|"&J85&"|"&K85 -> Liabilities|Portfolio investment, Debt securities, Long-term, Positions|Myanmar|Half-yearly, semester | B85: IMF.STA:PIP(5.0.0) | C85: NZL.L.P_F3_L_P_USD.S1.S1.MMR.S | D85: OBS_VALUE | E85: New Zealand | F85: Liabilities | G85: Portfolio investment, Debt securities, Long-term, Positions | H85: Total economy | I85: Total economy | J85: Myanmar | K85: Half-yearly, semester | L85: Millions
A86: =F86&"|"&G86&"|"&J86&"|"&K86 -> Liabilities|Portfolio investment, Debt securities, Long-term, Positions|Guam|Half-yearly, semester | B86: IMF.STA:PIP(5.0.0) | C86: NZL.L.P_F3_L_P_USD.S1.S1.GUM.S | D86: OBS_VALUE | E86: New Zealand | F86: Liabilities | G86: Portfolio investment, Debt securities, Long-term, Positions | H86: Total economy | I86: Total economy | J86: Guam | K86: Half-yearly, semester | L86: Millions
A87: =F87&"|"&G87&"|"&J87&"|"&K87 -> Liabilities|Portfolio investment, Debt securities, Positions|Bahrain, Kingdom of|Half-yearly, semester | B87: IMF.STA:PIP(5.0.0) | C87: NZL.L.P_F3_P_USD.S1.S1.BHR.S | D87: OBS_VALUE | E87: New Zealand | F87: Liabilities | G87: Portfolio investment, Debt securities, Positions | H87: Total economy | I87: Total economy | J87: Bahrain, Kingdom of | K87: Half-yearly, semester | L87: Millions | AL87: 0 | BI87: 0 | BM87: 0 | BO87: 0
A88: =F88&"|"&G88&"|"&J88&"|"&K88 -> Liabilities|Portfolio investment, Debt securities, Long-term, Positions|Bosnia and Herzegovina|Half-yearly, semester | B88: IMF.STA:PIP(5.0.0) | C88: NZL.L.P_F3_L_P_USD.S1.S1.BIH.S | D88: OBS_VALUE | E88: New Zealand | F88: Liabilities | G88: Portfolio investment, Debt securities, Long-term, Positions | H88: Total economy | I88: Total economy | J88: Bosnia and Herzegovina | K88: Half-yearly, semester | L88: Millions
A89: =F89&"|"&G89&"|"&J89&"|"&K89 -> Liabilities|Portfolio investment, Debt securities, Long-term, Positions|Tunisia|Half-yearly, semester | B89: IMF.STA:PIP(5.0.0) | C89: NZL.L.P_F3_L_P_USD.S1.S1.TUN.S | D89: OBS_VALUE | E89: New Zealand | F89: Liabilities | G89: Portfolio investment, Debt securities, Long-term, Positions | H89: Total economy | I89: Total economy | J89: Tunisia | K89: Half-yearly, semester | L89: Millions
A90: =F90&"|"&G90&"|"&J90&"|"&K90 -> Liabilities|Portfolio investment, Debt securities, Positions|Haiti|Half-yearly, semester | B90: IMF.STA:PIP(5.0.0) | C90: NZL.L.P_F3_P_USD.S1.S1.HTI.S | D90: OBS_VALUE | E90: New Zealand | F90: Liabilities | G90: Portfolio investment, Debt securities, Positions | H90: Total economy | I90: Total economy | J90: Haiti | K90: Half-yearly, semester | L90: Millions | AL90: 0 | BI90: 0 | BM90: 0 | BO90: 0
A91: =F91&"|"&G91&"|"&J91&"|"&K91 -> Liabilities|Portfolio investment, Debt securities, Positions|Monaco|Half-yearly, semester | B91: IMF.STA:PIP(5.0.0) | C91: NZL.L.P_F3_P_USD.S1.S1.MCO.S | D91: OBS_VALUE | E91: New Zealand | F91: Liabilities | G91: Portfolio investment, Debt securities, Positions | H91: Total economy | I91: Total economy | J91: Monaco | K91: Half-yearly, semester | L91: Millions | AL91: 0 | BI91: 0 | BM91: 0 | BO91: 0
A92: =F92&"|"&G92&"|"&J92&"|"&K92 -> Liabilities|Portfolio investment, Debt securities, Positions|Anguilla, United Kingdom-British Overseas Territory|Half-yearly, semester | B92: IMF.STA:PIP(5.0.0) | C92: NZL.L.P_F3_P_USD.S1.S1.AIA.S | D92: OBS_VALUE | E92: New Zealand | F92: Liabilities | G92: Portfolio investment, Debt securities, Positions | H92: Total economy | I92: Total economy | J92: Anguilla, United Kingdom-British Overseas Territory | K92: Half-yearly, semester | L92: Millions | AL92: 0 | BI92: 0 | BM92: 0 | BO92: 0
A93: =F93&"|"&G93&"|"&J93&"|"&K93 -> Liabilities|Portfolio investment, Debt securities, Positions|Portugal|Half-yearly, semester | B93: IMF.STA:PIP(5.0.0) | C93: NZL.L.P_F3_P_USD.S1.S1.PRT.S | D93: OBS_VALUE | E93: New Zealand | F93: Liabilities | G93: Portfolio investment, Debt securities, Positions | H93: Total economy | I93: Total economy | J93: Portugal | K93: Half-yearly, semester | L93: Millions | AL93: 0 | BI93: 0 | BM93: 0 | BO93: 0
A94: =F94&"|"&G94&"|"&J94&"|"&K94 -> Liabilities|Portfolio investment, Debt securities, Positions|Honduras|Half-yearly, semester | B94: IMF.STA:PIP(5.0.0) | C94: NZL.L.P_F3_P_USD.S1.S1.HND.S | D94: OBS_VALUE | E94: New Zealand | F94: Liabilities | G94: Portfolio investment, Debt securities, Positions | H94: Total economy | I94: Total economy | J94: Honduras | K94: Half-yearly, semester | L94: Millions | AL94: 0 | BI94: 0 | BM94: 0 | BO94: 0
A95: =F95&"|"&G95&"|"&J95&"|"&K95 -> Liabilities|Portfolio investment, Debt securities, Positions|Venezuela, República Bolivariana de|Half-yearly, semester | B95: IMF.STA:PIP(5.0.0) | C95: NZL.L.P_F3_P_USD.S1.S1.VEN.S | D95: OBS_VALUE | E95: New Zealand | F95: Liabilities | G95: Portfolio investment, Debt securities, Positions | H95: Total economy | I95: Total economy | J95: Venezuela, República Bolivariana de | K95: Half-yearly, semester | L95: Millions | AL95: 0 | BI95: 0 | BM95: 0 | BO95: 0
A96: =F96&"|"&G96&"|"&J96&"|"&K96 -> Liabilities|Portfolio investment, Debt securities, Positions|Chile|Half-yearly, semester | B96: IMF.STA:PIP(5.0.0) | C96: NZL.L.P_F3_P_USD.S1.S1.CHL.S | D96: OBS_VALUE | E96: New Zealand | F96: Liabilities | G96: Portfolio investment, Debt securities, Positions | H96: Total economy | I96: Total economy | J96: Chile | K96: Half-yearly, semester | L96: Millions | BI96: 0 | BM96: 0 | BO96: 0
A97: =F97&"|"&G97&"|"&J97&"|"&K97 -> Liabilities|Portfolio investment, Debt securities, Long-term, Positions|Brazil|Half-yearly, semester | B97: IMF.STA:PIP(5.0.0) | C97: NZL.L.P_F3_L_P_USD.S1.S1.BRA.S | D97: OBS_VALUE | E97: New Zealand | F97: Liabilities | G97: Portfolio investment, Debt securities, Long-term, Positions | H97: Total economy | I97: Total economy | J97: Brazil | K97: Half-yearly, semester | L97: Millions
A98: =F98&"|"&G98&"|"&J98&"|"&K98 -> Liabilities|Portfolio investment, Debt securities, Positions|Kiribati|Half-yearly, semester | B98: IMF.STA:PIP(5.0.0) | C98: NZL.L.P_F3_P_USD.S1.S1.KIR.S | D98: OBS_VALUE | E98: New Zealand | F98: Liabilities | G98: Portfolio investment, Debt securities, Positions | H98: Total economy | I98: Total economy | J98: Kiribati | K98: Half-yearly, semester | L98: Millions | AL98: 0 | BI98: 0 | BM98: 0 | BO98: 0
A99: =F99&"|"&G99&"|"&J99&"|"&K99 -> Liabilities|Portfolio investment, Debt securities, Positions|Turks and Caicos Islands|Half-yearly, semester | B99: IMF.STA:PIP(5.0.0) | C99: NZL.L.P_F3_P_USD.S1.S1.TCA.S | D99: OBS_VALUE | E99: New Zealand | F99: Liabilities | G99: Portfolio investment, Debt securities, Positions | H99: Total economy | I99: Total economy | J99: Turks and Caicos Islands | K99: Half-yearly, semester | L99: Millions | AL99: 0 | BI99: 0 | BM99: 0 | BO99: 0
A100: =F100&"|"&G100&"|"&J100&"|"&K100 -> Liabilities|Portfolio investment, Debt securities, Positions|Marshall Islands, Republic of the|Half-yearly, semester | B100: IMF.STA:PIP(5.0.0) | C100: NZL.L.P_F3_P_USD.S1.S1.MHL.S | D100: OBS_VALUE | E100: New Zealand | F100: Liabilities | G100: Portfolio investment, Debt securities, Positions | H100: Total economy | I100: Total economy | J100: Marshall Islands, Republic of the | K100: Half-yearly, semester | L100: Millions | AL100: 0 | BI100: 0 | BM100: 0 | BO100: 0
A101: =F101&"|"&G101&"|"&J101&"|"&K101 -> Liabilities|Portfolio investment, Debt securities, Positions|Ghana|Half-yearly, semester | B101: IMF.STA:PIP(5.0.0) | C101: NZL.L.P_F3_P_USD.S1.S1.GHA.S | D101: OBS_VALUE | E101: New Zealand | F101: Liabilities | G101: Portfolio investment, Debt securities, Positions | H101: Total economy | I101: Total economy | J101: Ghana | K101: Half-yearly, semester | L101: Millions | AL101: 0 | BI101: 0 | BM101: 0 | BO101: 0
A102: =F102&"|"&G102&"|"&J102&"|"&K102 -> Liabilities|Portfolio investment, Debt securities, Positions|San Marino, Republic of|Half-yearly, semester | B102: IMF.STA:PIP(5.0.0) | C102: NZL.L.P_F3_P_USD.S1.S1.SMR.S | D102: OBS_VALUE | E102: New Zealand | F102: Liabilities | G102: Portfolio investment, Debt securities, Positions | H102: Total economy | I102: Total economy | J102: San Marino, Republic of | K102: Half-yearly, semester | L102: Millions | AL102: 0 | BI102: 0 | BM102: 0 | BO102: 0
A103: =F103&"|"&G103&"|"&J103&"|"&K103 -> Liabilities|Portfolio investment, Debt securities, Positions|Uganda|Half-yearly, semester | B103: IMF.STA:PIP(5.0.0) | C103: NZL.L.P_F3_P_USD.S1.S1.UGA.S | D103: OBS_VALUE | E103: New Zealand | F103: Liabilities | G103: Portfolio investment, Debt securities, Positions | H103: Total economy | I103: Total economy | J103: Uganda | K103: Half-yearly, semester | L103: Millions | BI103: 0 | BM103: 0 | BO103: 0
A104: =F104&"|"&G104&"|"&J104&"|"&K104 -> Liabilities|Portfolio investment, Debt securities, Positions|Sierra Leone|Half-yearly, semester | B104: IMF.STA:PIP(5.0.0) | C104: NZL.L.P_F3_P_USD.S1.S1.SLE.S | D104: OBS_VALUE | E104: New Zealand | F104: Liabilities | G104: Portfolio investment, Debt securities, Positions | H104: Total economy | I104: Total economy | J104: Sierra Leone | K104: Half-yearly, semester | L104: Millions | AL104: 0 | BI104: 0 | BM104: 0 | BO104: 0
A105: =F105&"|"&G105&"|"&J105&"|"&K105 -> Liabilities|Portfolio investment, Debt securities, Positions|Guyana|Half-yearly, semester | B105: IMF.STA:PIP(5.0.0) | C105: NZL.L.P_F3_P_USD.S1.S1.GUY.S | D105: OBS_VALUE | E105: New Zealand | F105: Liabilities | G105: Portfolio investment, Debt securities, Positions | H105: Total economy | I105: Total economy | J105: Guyana | K105: Half-yearly, semester | L105: Millions | AL105: 0 | BI105: 0 | BM105: 0 | BO105: 0
A106: =F106&"|"&G106&"|"&J106&"|"&K106 -> Liabilities|Portfolio investment, Debt securities, Positions|Togo|Half-yearly, semester | B106: IMF.STA:PIP(5.0.0) | C106: NZL.L.P_F3_P_USD.S1.S1.TGO.S | D106: OBS_VALUE | E106: New Zealand | F106: Liabilities | G106: Portfolio investment, Debt securities, Positions | H106: Total economy | I106: Total economy | J106: Togo | K106: Half-yearly, semester | L106: Millions | AL106: 0 | BI106: 0 | BM106: 0 | BO106: 0
...

Sheet Calcs and Graphs
B1: 1997-S1 | C1: 1997-S2 | D1: 1998-S1 | E1: 1998-S2 | F1: 1999-S1 | G1: 1999-S2 | H1: 2000-S1 | I1: 2000-S2 | J1: 2001-S1 | K1: 2001-S2 | L1: 2002-S1 | M1: 2002-S2 | N1: 2003-S1 | O1: 2003-S2 | P1: 2004-S1 | Q1: 2004-S2 | R1: 2005-S1 | S1: 2005-S2 | T1: 2006-S1 | U1: 2006-S2 | V1: 2007-S1 | W1: 2007-S2 | X1: 2008-S1 | Y1: 2008-S2 | Z1: 2009-S1 | AA1: 2009-S2 | AB1: 2010-S1 | AC1: 2010-S2 | AD1: 2011-S1 | AE1: 2011-S2 | AF1: 2012-S1 | AG1: 2012-S2 | AH1: 2013-S1 | AI1: 2013-S2 | AJ1: 2014-S1 | AK1: 2014-S2 | AL1: 2015-S1 | AM1: 2015-S2 | AN1: 2016-S1 | AO1: 2016-S2 | AP1: 2017-S1 | AQ1: 2017-S2 | AR1: 2018-S1 | AS1: 2018-S2 | AT1: 2019-S1 | AU1: 2019-S2 | AV1: 2020-S1 | AW1: 2020-S2 | AX1: 2021-S1 | AY1: 2021-S2 | AZ1: 2022-S1 | BA1: 2022-S2 | BB1: 2023-S1 | BC1: 2023-S2 | BD1: 2024-S1 | BE1: 2024-S2 | BF1: 2025-S1 | BG1: 2025-S2
A2: HEADLINE: Debt securities, Positions (NZ-reported)
A3: World (row 320) | B3: =IF(raw_imf!M320="",NA(),raw_imf!M320) -> #N/A | C3: =IF(raw_imf!N320="",NA(),raw_imf!N320) -> #N/A | D3: =IF(raw_imf!O320="",NA(),raw_imf!O320) -> #N/A | E3: =IF(raw_imf!P320="",NA(),raw_imf!P320) -> #N/A | F3: =IF(raw_imf!Q320="",NA(),raw_imf!Q320) -> #N/A | G3: =IF(raw_imf!R320="",NA(),raw_imf!R320) -> #N/A | H3: =IF(raw_imf!S320="",NA(),raw_imf!S320) -> #N/A | I3: =IF(raw_imf!T320="",NA(),raw_imf!T320) -> #N/A | ... BG3: =IF(raw_imf!BR320="",NA(),raw_imf!BR320) -> 165011.17
A4: US (row 351) | B4: =IF(raw_imf!M351="",NA(),raw_imf!M351) -> #N/A | C4: =IF(raw_imf!N351="",NA(),raw_imf!N351) -> #N/A | D4: =IF(raw_imf!O351="",NA(),raw_imf!O351) -> #N/A | E4: =IF(raw_imf!P351="",NA(),raw_imf!P351) -> #N/A | F4: =IF(raw_imf!Q351="",NA(),raw_imf!Q351) -> #N/A | G4: =IF(raw_imf!R351="",NA(),raw_imf!R351) -> #N/A | H4: =IF(raw_imf!S351="",NA(),raw_imf!S351) -> #N/A | I4: =IF(raw_imf!T351="",NA(),raw_imf!T351) -> #N/A | ... BG4: =IF(raw_imf!BR351="",NA(),raw_imf!BR351) -> 38123.712
A5: Rest of World | B5: =B3-B4 -> #N/A | C5: =C3-C4 -> #N/A | D5: =D3-D4 -> #N/A | E5: =E3-E4 -> #N/A | F5: =F3-F4 -> #N/A | G5: =G3-G4 -> #N/A | H5: =H3-H4 -> #N/A | I5: =I3-I4 -> #N/A | ... BG5: =BG3-BG4 -> 126887.46
A6: Share US | B6: =B4/B3 -> #N/A | C6: =C4/C3 -> #N/A | D6: =D4/D3 -> #N/A | E6: =E4/E3 -> #N/A | F6: =F4/F3 -> #N/A | G6: =G4/G3 -> #N/A | H6: =H4/H3 -> #N/A | I6: =I4/I3 -> #N/A | ... BG6: =BG4/BG3 -> 0.23103716
A7: Share Rest of World | B7: =B5/B3 -> #N/A | C7: =C5/C3 -> #N/A | D7: =D5/D3 -> #N/A | E7: =E5/E3 -> #N/A | F7: =F5/F3 -> #N/A | G7: =G5/G3 -> #N/A | H7: =H5/H3 -> #N/A | I7: =I5/I3 -> #N/A | ... BG7: =BG5/BG3 -> 0.76896284
A8: Share Not Specified (row 383) | B8: =IF(raw_imf!M383="",NA(),raw_imf!M383)/B3 -> #N/A | C8: =IF(raw_imf!N383="",NA(),raw_imf!N383)/C3 -> #N/A | D8: =IF(raw_imf!O383="",NA(),raw_imf!O383)/D3 -> #N/A | E8: =IF(raw_imf!P383="",NA(),raw_imf!P383)/E3 -> #N/A | F8: =IF(raw_imf!Q383="",NA(),raw_imf!Q383)/F3 -> #N/A | G8: =IF(raw_imf!R383="",NA(),raw_imf!R383)/G3 -> #N/A | H8: =IF(raw_imf!S383="",NA(),raw_imf!S383)/H3 -> #N/A | I8: =IF(raw_imf!T383="",NA(),raw_imf!T383)/I3 -> #N/A | ... BG8: =IF(raw_imf!BR383="",NA(),raw_imf!BR383)/BG3 -> 0.40208665
A10: DERIVED: Positions, using counterparty information
A11: World (row 467) | B11: =IF(raw_imf!M467="",NA(),raw_imf!M467) -> #N/A | C11: =IF(raw_imf!N467="",NA(),raw_imf!N467) -> 10221.908 | D11: =IF(raw_imf!O467="",NA(),raw_imf!O467) -> #N/A | E11: =IF(raw_imf!P467="",NA(),raw_imf!P467) -> #N/A | F11: =IF(raw_imf!Q467="",NA(),raw_imf!Q467) -> #N/A | G11: =IF(raw_imf!R467="",NA(),raw_imf!R467) -> #N/A | H11: =IF(raw_imf!S467="",NA(),raw_imf!S467) -> #N/A | I11: =IF(raw_imf!T467="",NA(),raw_imf!T467) -> #N/A | ... BG11: =IF(raw_imf!BR467="",NA(),raw_imf!BR467) -> 89752.614
A12: US (row 468) | B12: =IF(raw_imf!M468="",NA(),raw_imf!M468) -> #N/A | C12: =IF(raw_imf!N468="",NA(),raw_imf!N468) -> 3469 | D12: =IF(raw_imf!O468="",NA(),raw_imf!O468) -> #N/A | E12: =IF(raw_imf!P468="",NA(),raw_imf!P468) -> #N/A | F12: =IF(raw_imf!Q468="",NA(),raw_imf!Q468) -> #N/A | G12: =IF(raw_imf!R468="",NA(),raw_imf!R468) -> #N/A | H12: =IF(raw_imf!S468="",NA(),raw_imf!S468) -> #N/A | I12: =IF(raw_imf!T468="",NA(),raw_imf!T468) -> #N/A | ... BG12: =IF(raw_imf!BR468="",NA(),raw_imf!BR468) -> 17327
A13: Rest of World | B13: =B11-B12 -> #N/A | C13: =C11-C12 -> 6752.9076 | D13: =D11-D12 -> #N/A | E13: =E11-E12 -> #N/A | F13: =F11-F12 -> #N/A | G13: =G11-G12 -> #N/A | H13: =H11-H12 -> #N/A | I13: =I11-I12 -> #N/A | ... BG13: =BG11-BG12 -> 72425.614
A14: Share US | B14: =B12/B11 -> #N/A | C14: =C12/C11 -> 0.33936914 | D14: =D12/D11 -> #N/A | E14: =E12/E11 -> #N/A | F14: =F12/F11 -> #N/A | G14: =G12/G11 -> #N/A | H14: =H12/H11 -> #N/A | I14: =I12/I11 -> #N/A | ... BG14: =BG12/BG11 -> 0.19305287
A15: Share Rest of World | B15: =B13/B11 -> #N/A | C15: =C13/C11 -> 0.66063086 | D15: =D13/D11 -> #N/A | E15: =E13/E11 -> #N/A | F15: =F13/F11 -> #N/A | G15: =G13/G11 -> #N/A | H15: =H13/H11 -> #N/A | I15: =I13/I11 -> #N/A | ... BG15: =BG13/BG11 -> 0.80694713
A17: New Zealand Announced Debt | B17: =B3 -> #N/A | C17: =C3 -> #N/A | D17: =D3 -> #N/A | E17: =E3 -> #N/A | F17: =F3 -> #N/A | G17: =G3 -> #N/A | H17: =H3 -> #N/A | I17: =I3 -> #N/A | ... BG17: =BG3 -> 165011.17
A18: US Treasuary Announced Debt to IMF (Backup is New Zealand guess) | B18: =IFERROR(B12,B4) -> #N/A | C18: =IFERROR(C12,C4) -> 3469 | D18: =IFERROR(D12,D4) -> #N/A | E18: =IFERROR(E12,E4) -> #N/A | F18: =IFERROR(F12,F4) -> #N/A | G18: =IFERROR(G12,G4) -> #N/A | H18: =IFERROR(H12,H4) -> #N/A | I18: =IFERROR(I12,I4) -> #N/A | ... BG18: =IFERROR(BG12,BG4) -> 17327
A19: Percentage US | B19: =B18/B17 -> #N/A | C19: =C18/C17 -> #N/A | D19: =D18/D17 -> #N/A | E19: =E18/E17 -> #N/A | F19: =F18/F17 -> #N/A | G19: =G18/G17 -> #N/A | H19: =H18/H17 -> #N/A | I19: =I18/I17 -> #N/A | ... BG19: =BG18/BG17 -> 0.10500501
A20: Percentage World | B20: =1-B19 -> #N/A | C20: =1-C19 -> #N/A | D20: =1-D19 -> #N/A | E20: =1-E19 -> #N/A | F20: =1-F19 -> #N/A | G20: =1-G19 -> #N/A | H20: =1-H19 -> #N/A | I20: =1-I19 -> #N/A | ... BG20: =1-BG19 -> 0.89499499
A22: RATIONALE

Sheet Intermediate Calcs
A1: date | B1: us_share
A2: {=TRANSPOSE(IF(ISBLANK('Calcs and Graphs'!AJ1:BG1), "", DATE(LEFT('Calcs and Graphs'!AJ1:BG1, 4), (RIGHT('Calcs and Graphs'!AJ1:BG1, 1) * 6) - 5, 1)))} -> 41640 | B2: {=TRANSPOSE('Calcs and Graphs'!AJ19:BG19)} -> 0.15802166
A3: 41821 | B3: 0.17697616
A4: 42005 | B4: 0.15258105
A5: 42186 | B5: 0.1597423
A6: 42370 | B6: 0.14949813
A7: 42552 | B7: 0.13364519
A8: 42736 | B8: 0.11804457
A9: 42917 | B9: 0.10106066
A10: 43101 | B10: 0.11602954
A11: 43282 | B11: 0.12425947
A12: 43466 | B12: 0.11809973
A13: 43647 | B13: 0.13588698
A14: 43831 | B14: 0.11752606
... A25: 45839 | B25: 0.10500501

Sheet Regression Series
A1: date | B1: us_share
A2: {=SEQUENCE(DATE(2026,1,1)-DATE(2014,1,1)+1,1,DATE(2014,1,1))} -> 41640 | B2: {=IF(ISBLANK(A2:A5158), "", VLOOKUP(A2:A5158, 'Intermediate Calcs'!A2:B25, 2, TRUE))} -> 0.15802166
A3: 41641 | B3: 0.15802166
A4: 41642 | B4: 0.15802166
A5: 41643 | B5: 0.15802166
A6: 41644 | B6: 0.15802166
A7: 41645 | B7: 0.15802166
A8: 41646 | B8: 0.15802166
A9: 41647 | B9: 0.15802166
A10: 41648 | B10: 0.15802166
A11: 41649 | B11: 0.15802166
A12: 41650 | B12: 0.15802166
A13: 41651 | B13: 0.15802166
A14: 41652 | B14: 0.15802166
... A4385: 46023 | B4385: 0.10500501
